logitsai/__init__.py
logitsai-0.0.1.dist-info/METADATA
logitsai-0.0.1.dist-info/WHEEL
logitsai-0.0.1.dist-info/top_level.txt
logitsai-0.0.1.dist-info/RECORD
